nibble-0.1.0.dist-info/DESCRIPTION.rst
nibble-0.1.0.dist-info/METADATA
nibble-0.1.0.dist-info/metadata.json
nibble-0.1.0.dist-info/entry_points.txt
nibble-0.1.0.dist-info/top_level.txt
nibble-0.1.0.dist-info/zip-safe
nibble-0.1.0.dist-info/WHEEL
nibble-0.1.0.dist-info/RECORD
nibble/decorators.py
nibble/__init__.py
nibble/information.py
nibble/speed.py
nibble/duration.py
nibble/tests/test_duration.py
nibble/tests/test_decorators.py
nibble/tests/test_speed.py
nibble/tests/__init__.py
nibble/tests/test_information.py
